LICENSE
MANIFEST.in
README.rst
setup.py
djangocms_glyphicon_awesome/__init__.py
djangocms_glyphicon_awesome/admin.py
djangocms_glyphicon_awesome/models.py
djangocms_glyphicon_awesome/tests.py
djangocms_glyphicon_awesome/views.py
djangocms_glyphicon_awesome.egg-info/PKG-INFO
djangocms_glyphicon_awesome.egg-info/SOURCES.txt
djangocms_glyphicon_awesome.egg-info/dependency_links.txt
djangocms_glyphicon_awesome.egg-info/not-zip-safe
djangocms_glyphicon_awesome.egg-info/top_level.txt
djangocms_glyphicon_awesome/static/djangocms_text_ckeditor/ckeditor/config.js
djangocms_glyphicon_awesome/static/djangocms_text_ckeditor/ckeditor/plugins/glyphicons/installation.txt
djangocms_glyphicon_awesome/static/djangocms_text_ckeditor/ckeditor/plugins/glyphicons/logs.txt
djangocms_glyphicon_awesome/static/djangocms_text_ckeditor/ckeditor/plugins/glyphicons/plugin.js
djangocms_glyphicon_awesome/static/djangocms_text_ckeditor/ckeditor/plugins/glyphicons/bootstrap/config.json
djangocms_glyphicon_awesome/static/djangocms_text_ckeditor/ckeditor/plugins/glyphicons/bootstrap/css/bootstrap.css
djangocms_glyphicon_awesome/static/djangocms_text_ckeditor/ckeditor/plugins/glyphicons/bootstrap/fonts/glyphicons-halflings-regular.eot
djangocms_glyphicon_awesome/static/djangocms_text_ckeditor/ckeditor/plugins/glyphicons/bootstrap/fonts/glyphicons-halflings-regular.svg
djangocms_glyphicon_awesome/static/djangocms_text_ckeditor/ckeditor/plugins/glyphicons/bootstrap/fonts/glyphicons-halflings-regular.ttf
djangocms_glyphicon_awesome/static/djangocms_text_ckeditor/ckeditor/plugins/glyphicons/bootstrap/fonts/glyphicons-halflings-regular.woff
djangocms_glyphicon_awesome/static/djangocms_text_ckeditor/ckeditor/plugins/glyphicons/dialogs/glyphicons.js
djangocms_glyphicon_awesome/static/djangocms_text_ckeditor/ckeditor/plugins/glyphicons/icons/glyphicons.png
djangocms_glyphicon_awesome/static/djangocms_text_ckeditor/ckeditor/plugins/lineutils/plugin.js
djangocms_glyphicon_awesome/static/djangocms_text_ckeditor/ckeditor/plugins/lineutils/dev/dnd.html
djangocms_glyphicon_awesome/static/djangocms_text_ckeditor/ckeditor/plugins/lineutils/dev/magicfinger.html
djangocms_glyphicon_awesome/static/djangocms_text_ckeditor/ckeditor/plugins/widget/plugin.js
