Metadata-Version: 1.0
Name: djangocms-glyphicon-awesome
Version: 0.1.0
Summary: A plugin to incorporate Glyphicon and Font Awesome into djangocms-text-ckeditor
Home-page: http://github.com/georgema1982/djangocms-glyphicon-awesome
Author: George Ma
Author-email: george.ma1982@gmail.com
License: MIT
Platform: UNKNOWN
Classifier: Development Status :: 3 - Alpha
Classifier: Framework :: Django
Classifier: Intended Audience :: Developers
Classifier: License :: OSI Approved :: MIT License
Classifier: Operating System :: OS Independent
Classifier: Programming Language :: Python
Classifier: Topic :: Internet :: WWW/HTTP
